README.md
setup.cfg
setup.py
thorlabs_apt/_APTAPI.py
thorlabs_apt/__init__.py
thorlabs_apt/_error_codes.py
thorlabs_apt/core.py
thorlabs_apt.egg-info/PKG-INFO
thorlabs_apt.egg-info/SOURCES.txt
thorlabs_apt.egg-info/dependency_links.txt
thorlabs_apt.egg-info/top_level.txt